pygamenu/__init__.py
pygamenu/compiler/__init__.py
pygamenu/compiler/errors.py
pygamenu/compiler/pmscript.py
pygamenu/mainn/__init__.py
pygamenu/mainn/eventlistener.py
pygamenu/mainn/main.py
pygamenu/utils/__init__.py
pygamenu/utils/logging.py
pygamenu-0.0.59.dist-info/licenses/LICENSE
pygamenu-0.0.59.dist-info/METADATA
pygamenu-0.0.59.dist-info/WHEEL
pygamenu-0.0.59.dist-info/top_level.txt
pygamenu-0.0.59.dist-info/RECORD
