Metadata-Version: 2.4
Name: pygamenu
Version: 0.0.59
Summary: A neat little pygame wrapper
Home-page: https://github.com/Camleaf/Pymenu
Classifier: Programming Language :: Python :: 3
Classifier: License :: OSI Approved :: MIT License
Classifier: Operating System :: OS Independent
Requires-Python: >=3.11.9
License-File: LICENSE
Requires-Dist: pygame-ce
Dynamic: license-file
